LICENSE.md
README.md
react_tk/__init__.py
react_tk/interaction/scheduler.py
react_tk/props/annotations/__init__.py
react_tk/props/annotations/create_props.py
react_tk/props/annotations/decorators.py
react_tk/props/annotations/prop_meta.py
react_tk/props/annotations/shadow_reflector.py
react_tk/props/impl/__init__.py
react_tk/props/impl/common.py
react_tk/props/impl/prop.py
react_tk/props/impl/v_mapping.py
react_tk/py.typed
react_tk/reflect/accessor/base.py
react_tk/reflect/accessor/type.py
react_tk/reflect/reader/base.py
react_tk/reflect/reader/generic.py
react_tk/reflect/reader/type.py
react_tk/reflect/reflector.py
react_tk/renderable/component.py
react_tk/renderable/context.py
react_tk/renderable/node/__init__.py
react_tk/renderable/node/prop_value_accessor.py
react_tk/renderable/node/shadow_node.py
react_tk/renderable/node/top.py
react_tk/renderable/renderable_base.py
react_tk/renderable/trace.py
react_tk/rendering/actions/actions.py
react_tk/rendering/actions/compute.py
react_tk/rendering/actions/node_reconciler.py
react_tk/rendering/actions/reconcile_state.py
react_tk/rendering/actions/top_reconciler.py
react_tk/rendering/component/render_sink.py
react_tk/rendering/render_root.py
react_tk/tk/mount.py
react_tk/tk/nodes/button.py
react_tk/tk/nodes/frame.py
react_tk/tk/nodes/label.py
react_tk/tk/nodes/tool_tip_label.py
react_tk/tk/nodes/widget.py
react_tk/tk/nodes/window.py
react_tk/tk/props/background.py
react_tk/tk/props/border.py
react_tk/tk/props/clickable.py
react_tk/tk/props/handler.py
react_tk/tk/props/label.py
react_tk/tk/props/pack.py
react_tk/tk/props/padding.py
react_tk/tk/props/text.py
react_tk/tk/props/width_height.py
react_tk/tk/reconcilers/widget_reconciler.py
react_tk/tk/reconcilers/window_reconciler.py
react_tk/tk/types/font.py
react_tk/tk/types/geometry.py
react_tk/tk/types/padding.py
react_tk/tk/util/tk.py
react_tk/tk/widget_data.py
react_tk/tk/win32/tweaks.py
react_tk/util/async_loop.py
react_tk/util/core_reflection.py
react_tk/util/dict.py
react_tk-0.4.10.dist-info/METADATA
react_tk-0.4.10.dist-info/WHEEL
react_tk-0.4.10.dist-info/licenses/LICENSE.md
react_tk-0.4.10.dist-info/RECORD
