Metadata-Version: 2.4
Name: react-tk
Version: 0.4.10
Summary: Build Tkinter UIs the React way
License: MIT
License-File: LICENSE.md
Author: GregRos
Author-email: gregros@gregros.dev
Requires-Python: >=3.12,<3.15
Classifier: License :: OSI Approved :: MIT License
Classifier: Programming Language :: Python :: 3
Classifier: Programming Language :: Python :: 3.12
Classifier: Programming Language :: Python :: 3.13
Classifier: Programming Language :: Python :: 3.14
Requires-Dist: expression (>=5.6.0,<6.0.0)
Requires-Dist: funcy (>=2.0,<3.0)
Requires-Dist: funcy-typing (>=2.0.8,<3.0.0)
Requires-Dist: pywin32 (>=311,<312) ; sys_platform == "win32"
Requires-Dist: typeguard (>=4.4.0,<5.0.0)
